css_tidy/__init__.py
css_tidy/__init__.pyi
css_tidy/cli.py
css_tidy/tidy.py
css_tidy-0.1.7.dist-info/licenses/LICENSE
css_tidy-0.1.7.dist-info/METADATA
css_tidy-0.1.7.dist-info/WHEEL
css_tidy-0.1.7.dist-info/entry_points.txt
css_tidy-0.1.7.dist-info/top_level.txt
css_tidy-0.1.7.dist-info/RECORD
