Metadata-Version: 2.4
Name: css-tidy
Version: 0.1.7
Summary: A Python tool to tidy and format CSS files
Home-page: https://github.com/henrylok/css-tidy
Author: Henry Lok
Author-email: Henry Lok <henry.lok@example.com>
Maintainer-email: Henry Lok <henry.lok@example.com>
License: MIT
Project-URL: Homepage, https://github.com/henrylok/css-tidy
Project-URL: Documentation, https://github.com/henrylok/css-tidy#readme
Project-URL: Repository, https://github.com/henrylok/css-tidy
Project-URL: Bug Tracker, https://github.com/henrylok/css-tidy/issues
Keywords: css,formatting,tidy,beautify,minify
Classifier: Development Status :: 3 - Alpha
Classifier: Intended Audience :: Developers
Classifier: License :: OSI Approved :: MIT License
Classifier: Operating System :: OS Independent
Classifier: Programming Language :: Python :: 3
Classifier: Programming Language :: Python :: 3.7
Classifier: Programming Language :: Python :: 3.8
Classifier: Programming Language :: Python :: 3.9
Classifier: Programming Language :: Python :: 3.10
Classifier: Programming Language :: Python :: 3.11
Classifier: Topic :: Software Development :: Libraries :: Python Modules
Classifier: Topic :: Text Processing :: Markup
Classifier: Topic :: Utilities
Requires-Python: >=3.7
License-File: LICENSE
Requires-Dist: click>=8.0.0
Requires-Dist: colorama>=0.4.4
Provides-Extra: dev
Requires-Dist: pytest>=6.0.0; extra == "dev"
Requires-Dist: black>=21.0.0; extra == "dev"
Requires-Dist: flake8>=3.8.0; extra == "dev"
Requires-Dist: mypy>=0.900; extra == "dev"
Dynamic: author
Dynamic: home-page
Dynamic: license-file
Dynamic: requires-python
